ArchitectureFPGA/LUT2.sv
`timescale 1ns/1ns

module LUT2 (O, I0, I1);

    parameter INIT = 4'h08;

    input logic I0, I1;
    output logic O;

    logic [1:0] s;

    assign s = {I1, I0};

    always_ff @(s) begin
        if ((s[1]^s[0] == 1) || (s[1]^s[0] == 0))
            O = INIT[s];
        else if ((INIT[0] == INIT[1]) && (INIT[2] == INIT[3]) && (INIT[0] == INIT[2]))
            O = INIT[0];
        else if ((s[1] == 0) && (INIT[0] == INIT[1]))
            O = INIT[0];
        else if ((s[1] == 1) && (INIT[2] == INIT[3]))
            O = INIT[2];
        else if ((s[0] == 0) && (INIT[0] == INIT[2]))
            O = INIT[0];
        else if ((s[0] == 1) && (INIT[1] == INIT[3]))
            O = INIT[1];
        else
            O = 1'bx;
    end

endmodule

Ex1.sv
`timescale 1ns/1ns

module Ex1 (A,B,C,D,Y);
    input logic A,B,C,D;
    output logic Y;

    wire [2:0] w;

    LUT2 #(.INIT(4'h7)) L2NAND1( .I0(A), .I1(B), .O(w[0]) );
    LUT2 #(.INIT(4'h7)) L2NAND2( .I0(C), .I1(w[0]), .O(w[1]) );
    LUT2 #(.INIT(4'h7)) L2NAND3( .I0(C), .I1(D), .O(w[2]) );

    LUT2 #(.INIT(4'h1)) L2NOR4( .I0(w[1]), .I1(w[2]), .O(Y) );

endmodule

Ex1_tb.sv
module Ex1_tb;
    logic A,B,C,D;
    logic Y;

    Ex1 ex1t( .A(A), .B(B), .C(C), .D(D), .Y(Y));

    initial begin
        integer i;

        for (i=0;i<16;i++) begin
            {A, B, C, D} = i[3:0];
            #5;

            $display($time, ("    | %b  %b  %b  %b || %b"), A, B, C, D, Y);
        end
    end

    /*initial begin
        $monitor($time, ("    | %b  %b  %b  %b || %b"), A, B, C, D, Y);
    end*/

    initial begin
        $dumpfile("Ex1.vcd");
        $dumpvars("");
    end

endmodule

Ex1.vcd
$version Generated by VerilatedVcd $end
$timescale 1ns $end
 $scope module $rootio $end
 $upscope $end
 $scope module Ex1_tb $end
  $var wire 1 # A $end
  $var wire 1 $ B $end
  $var wire 1 % C $end
  $var wire 1 & D $end
  $var wire 1 * Y $end
  $scope module ex1t $end
   $var wire 1 # A $end
   $var wire 1 $ B $end
   $var wire 1 % C $end
   $var wire 1 & D $end
   $var wire 1 * Y $end
   $var wire 3 + w [2:0] $end
   $scope module L2NAND1 $end
    $var wire 4 1 INIT [3:0] $end
    $var wire 1 # I0 $end
    $var wire 1 $ I1 $end
    $var wire 1 , O $end
    $var wire 2 ' s [1:0] $end
   $upscope $end
   $scope module L2NAND2 $end
    $var wire 4 1 INIT [3:0] $end
    $var wire 1 % I0 $end
    $var wire 1 , I1 $end
    $var wire 1 - O $end
    $var wire 2 0 s [1:0] $end
   $upscope $end
   $scope module L2NAND3 $end
    $var wire 4 1 INIT [3:0] $end
    $var wire 1 % I0 $end
    $var wire 1 & I1 $end
    $var wire 1 . O $end
    $var wire 2 ( s [1:0] $end
   $upscope $end
   $scope module L2NOR4 $end
    $var wire 4 2 INIT [3:0] $end
    $var wire 1 - I0 $end
    $var wire 1 . I1 $end
    $var wire 1 * O $end
    $var wire 2 / s [1:0] $end
   $upscope $end
  $upscope $end
  $scope module unnamedblk1 $end
   $var wire 32 ) i [31:0] $end
  $upscope $end
 $upscope $end
$enddefinitions $end


#0
0#
0$
0%
0&
b00 '
b00 (
b00000000000000000000000000000000 )
0*
b111 +
1,
1-
1.
b11 /
b10 0
b0111 1
b0001 2
#5
1&
b10 (
b00000000000000000000000000000001 )
#10
1%
0&
b01 (
b00000000000000000000000000000010 )
b101 +
0-
b10 /
b11 0
#15
1&
b11 (
b00000000000000000000000000000011 )
1*
b001 +
0.
b00 /
#20
1$
0%
0&
b10 '
b00 (
b00000000000000000000000000000100 )
0*
b111 +
1-
1.
b11 /
b10 0
#25
1&
b10 (
b00000000000000000000000000000101 )
#30
1%
0&
b01 (
b00000000000000000000000000000110 )
b101 +
0-
b10 /
b11 0
#35
1&
b11 (
b00000000000000000000000000000111 )
1*
b001 +
0.
b00 /
#40
1#
0$
0%
0&
b01 '
b00 (
b00000000000000000000000000001000 )
0*
b111 +
1-
1.
b11 /
b10 0
#45
1&
b10 (
b00000000000000000000000000001001 )
#50
1%
0&
b01 (
b00000000000000000000000000001010 )
b101 +
0-
b10 /
b11 0
#55
1&
b11 (
b00000000000000000000000000001011 )
1*
b001 +
0.
b00 /
#60
1$
0%
0&
b11 '
b00 (
b00000000000000000000000000001100 )
0*
b110 +
0,
1-
1.
b11 /
b00 0
#65
1&
b10 (
b00000000000000000000000000001101 )
#70
1%
0&
b01 (
b00000000000000000000000000001110 )
b01 0
#75
1&
b11 (
b00000000000000000000000000001111 )
b010 +
0.
b01 /
#80
b00000000000000000000000000010000 )
