LUT3.sv
// $Header: /devl/xcs/repo/env/Databases/CAEInterfaces/verunilibs/data/unisims/LUT3.v,v 1.7 2007/05/23 21:43:39 patrickp Exp $
///////////////////////////////////////////////////////////////////////////////
// Copyright (c) 1995/2004 Xilinx, Inc.
// All Right Reserved.
///////////////////////////////////////////////////////////////////////////////
//   ____  ____
//  /   /\/   /
// /___/  \  /    Vendor : Xilinx
// \   \   \/     Version : 10.1
//  \   \         Description : Xilinx Functional Simulation Library Component
//  /   /                  3-input Look-Up-Table with General Output
// /___/   /\     Filename : LUT3.v
// \   \  /  \    Timestamp : Thu Mar 25 16:42:54 PST 2004
//  \___\/\___\
//
// Revision:
//    03/23/04 - Initial version.
//    02/04/05 - Rev 0.0.1 Replace premitive with function; Remove buf.
//    05/23/07 - Changed timescale to 1 ps / 1 ps.

`timescale  1 ns / 1 ns


module LUT3 (O, I0, I1, I2);

    parameter INIT = 8'h00;

    input I0, I1, I2;

    output logic O;

    logic tmp;
  
    always_ff @(  I2 or  I1 or  I0 )  begin
      tmp <=  I0 ^ I1  ^ I2;
      if ( tmp == 0 || tmp == 1)
           O <= INIT[{I2, I1, I0}];
      else
           O <= lut3_mux4 ( {1'b0, 1'b0, lut3_mux4 (INIT[7:4], {I1, I0}),
                          lut3_mux4 (INIT[3:0], {I1, I0}) }, {1'b0, I2});
    end

  function lut3_mux4;
  input [3:0] d;
  input [1:0] s;

  begin
       if ((s[1]^s[0] ==1) || (s[1]^s[0] ==0))
           lut3_mux4 = d[s];
         else if ((d[0] === d[1]) && (d[2] === d[3]) && (d[0] === d[2]))
           lut3_mux4 = d[0];
         else if ((s[1] == 0) && (d[0] === d[1]))
           lut3_mux4 = d[0];
         else if ((s[1] == 1) && (d[2] === d[3]))
           lut3_mux4 = d[2];
         else if ((s[0] == 0) && (d[0] === d[2]))
           lut3_mux4 = d[0];
         else if ((s[0] == 1) && (d[1] === d[3]))
           lut3_mux4 = d[1];
         else
           lut3_mux4 = 1'bx;
   end
   endfunction

endmodule

ArchitectureFPGA/LUT2.sv
`timescale 1ns/1ns

module LUT2 (O, I0, I1);

    parameter INIT = 4'h08;

    input logic I0, I1;
    output logic O;

    logic [1:0] s;

    assign s = {I1, I0};

    always_ff @(s) begin
        if ((s[1]^s[0] == 1) || (s[1]^s[0] == 0))
            O = INIT[s];
        else if ((INIT[0] == INIT[1]) && (INIT[2] == INIT[3]) && (INIT[0] == INIT[2]))
            O = INIT[0];
        else if ((s[1] == 0) && (INIT[0] == INIT[1]))
            O = INIT[0];
        else if ((s[1] == 1) && (INIT[2] == INIT[3]))
            O = INIT[2];
        else if ((s[0] == 0) && (INIT[0] == INIT[2]))
            O = INIT[0];
        else if ((s[0] == 1) && (INIT[1] == INIT[3]))
            O = INIT[1];
        else
            O = 1'bx;
    end

endmodule

Ex3.sv
`timescale 1ns/1ns

module Ex3 (A,B,Ci,Co,S);
    input logic A, B, Ci;
    output logic Co, S;

    wire [2:0] w;

    LUT3 #(.INIT(8'h96)) L3XOR1 ( .O(S), .I0(A), .I1(B), .I2(Ci) );

    LUT2 #(.INIT(4'h8)) L2AND1 ( .O(w[0]), .I0(Ci), .I1(B) );
    LUT2 #(.INIT(4'h8)) L2AND2 ( .O(w[1]), .I0(A), .I1(B) );
    LUT2 #(.INIT(4'h8)) L2AND3 ( .O(w[2]), .I0(Ci), .I1(A) );
    LUT3 #(.INIT(8'hFE)) L3OR1 ( .O(Co), .I0(w[0]), .I1(w[1]), .I2(w[2]) );

endmodule

Ex3_tb.sv
module Ex3_tb;
    logic A, B, Ci, Co, S;

    Ex3 ex3t ( .A(A), .B(B), .Ci(Ci), .Co(Co), .S(S));

    initial begin
        for (int i=0; i<8; ++i) begin
            {A, B, Ci} = i[2:0];
            
            #5;
            $display($time, ("  %b %b %b || %b %b "), A,B,Ci,Co,S);
        end
        #5;
    end

    /*initial begin
        $monitor(("%0d  %b %b %b || %b %b "), $time, A,B,Ci,Co,S);
    end*/

    initial begin
        $dumpfile("Ex3.vcd");
        $dumpvars("");
    end

endmodule

Ex3.vcd
$version Generated by VerilatedVcd $end
$timescale 1ns $end
 $scope module $rootio $end
 $upscope $end
 $scope module Ex3_tb $end
  $var wire 1 # A $end
  $var wire 1 $ B $end
  $var wire 1 % Ci $end
  $var wire 1 . Co $end
  $var wire 1 / S $end
  $scope module ex3t $end
   $var wire 1 # A $end
   $var wire 1 $ B $end
   $var wire 1 % Ci $end
   $var wire 1 . Co $end
   $var wire 1 / S $end
   $var wire 3 * w [2:0] $end
   $scope module L2AND1 $end
    $var wire 4 2 INIT [3:0] $end
    $var wire 1 % I0 $end
    $var wire 1 $ I1 $end
    $var wire 1 + O $end
    $var wire 2 & s [1:0] $end
   $upscope $end
   $scope module L2AND2 $end
    $var wire 4 2 INIT [3:0] $end
    $var wire 1 # I0 $end
    $var wire 1 $ I1 $end
    $var wire 1 , O $end
    $var wire 2 ' s [1:0] $end
   $upscope $end
   $scope module L2AND3 $end
    $var wire 4 2 INIT [3:0] $end
    $var wire 1 % I0 $end
    $var wire 1 # I1 $end
    $var wire 1 - O $end
    $var wire 2 ( s [1:0] $end
   $upscope $end
   $scope module L3OR1 $end
    $var wire 8 3 INIT [7:0] $end
    $var wire 1 + I0 $end
    $var wire 1 , I1 $end
    $var wire 1 - I2 $end
    $var wire 1 . O $end
    $var wire 1 0 tmp $end
   $upscope $end
   $scope module L3XOR1 $end
    $var wire 8 4 INIT [7:0] $end
    $var wire 1 # I0 $end
    $var wire 1 $ I1 $end
    $var wire 1 % I2 $end
    $var wire 1 / O $end
    $var wire 1 1 tmp $end
   $upscope $end
  $upscope $end
  $scope module unnamedblk1 $end
   $var wire 32 ) i [31:0] $end
  $upscope $end
 $upscope $end
$enddefinitions $end


#0
0#
0$
0%
b00 &
b00 '
b00 (
b00000000000000000000000000000000 )
b000 *
0+
0,
0-
0.
0/
00
01
b1000 2
b11111110 3
b10010110 4
#5
1%
b01 &
b01 (
b00000000000000000000000000000001 )
1/
11
#10
1$
0%
b10 &
b10 '
b00 (
b00000000000000000000000000000010 )
#15
1%
b11 &
b01 (
b00000000000000000000000000000011 )
b001 *
1+
1.
0/
10
01
#20
1#
0$
0%
b00 &
b01 '
b10 (
b00000000000000000000000000000100 )
b000 *
0+
0.
1/
00
11
#25
1%
b01 &
b11 (
b00000000000000000000000000000101 )
b100 *
1-
1.
0/
10
01
#30
1$
0%
b10 &
b11 '
b10 (
b00000000000000000000000000000110 )
b010 *
1,
0-
#35
1%
b11 &
b11 (
b00000000000000000000000000000111 )
b111 *
1+
1-
1/
11
#40
b00000000000000000000000000001000 )
