Gates/fulladdsub.sv
`timescale 1ns/1ns

module fulladdsub (
    input logic A, B, SEL, CI,
    output logic Y, CO
);

    assign Y = A^B^CI;
    assign CO = (CI&B) | (B|CI)&(SEL^A);
endmodule

qfas.sv
`timescale 1ns/1ns

module qfas (
    input logic [3:0] A, B,
    input logic SEL, CI,
    output logic [3:0] Y,
    output logic CO
);

    logic [2:0] W;

    fulladdsub  Bit0 (  .A(A[0]), .B(B[0]), .SEL(SEL), .CI(CI),   .Y(Y[0]), .CO(W[0]) );
    fulladdsub  Bit1 (  .A(A[1]), .B(B[1]), .SEL(SEL), .CI(W[0]), .Y(Y[1]), .CO(W[1]) );
    fulladdsub  Bit2 (  .A(A[2]), .B(B[2]), .SEL(SEL), .CI(W[1]), .Y(Y[2]), .CO(W[2]) );
    fulladdsub  Bit3 (  .A(A[3]), .B(B[3]), .SEL(SEL), .CI(W[2]), .Y(Y[3]), .CO(CO)   );

endmodule

qfas_tb.sv
module qfas_tb;
    logic [3:0] A, B;
    logic SEL, CI;
    logic [3:0] Y;
    logic CO;

    qfas qfasg ( .A(A), .B(B), .SEL(SEL), .CI(CI), .Y(Y), .CO(CO));

    initial begin
        SEL = 1'b0;
        CI = 1'b0;
        A = 4'b0011;
        B = 4'b0011;

        #5
        A = 4'b0101;
        B = 4'b1010;

        #5
        A = 4'b0100;
        B = 4'b0011;

        #5
        A = 4'b1010;
        B = 4'b1011;

        #5
        SEL = 1'b1;
        CI = 1'b0;
        A = 4'b0011;
        B = 4'b0011;

        #5
        A = 4'b0101;
        B = 4'b1010;

        #5
        A = 4'b0100;
        B = 4'b0011;

        #5
        A = 4'b1010;
        B = 4'b1011;
    end

    initial begin
        $monitor($time, " SEL=%b CI=%b A=%b B=%b | OUT= %b%b", SEL, CI, A, B, CO, Y);
    end

    initial begin
        $dumpfile("qfas.vcd");
        $dumpvars("");
    end
endmodule

qfas.vcd
$version Generated by VerilatedVcd $end
$timescale 1ps $end
 $scope module $rootio $end
 $upscope $end
 $scope module qfas_tb $end
  $var wire 4 # A [3:0] $end
  $var wire 4 $ B [3:0] $end
  $var wire 1 % SEL $end
  $var wire 1 & CI $end
  $var wire 4 / Y [3:0] $end
  $var wire 1 0 CO $end
  $scope module qfasg $end
   $var wire 4 # A [3:0] $end
   $var wire 4 $ B [3:0] $end
   $var wire 1 % SEL $end
   $var wire 1 & CI $end
   $var wire 4 / Y [3:0] $end
   $var wire 1 0 CO $end
   $var wire 3 1 W [2:0] $end
   $scope module Bit0 $end
    $var wire 1 ' A $end
    $var wire 1 ( B $end
    $var wire 1 % SEL $end
    $var wire 1 & CI $end
    $var wire 1 2 Y $end
    $var wire 1 3 CO $end
   $upscope $end
   $scope module Bit1 $end
    $var wire 1 ) A $end
    $var wire 1 * B $end
    $var wire 1 % SEL $end
    $var wire 1 3 CI $end
    $var wire 1 4 Y $end
    $var wire 1 5 CO $end
   $upscope $end
   $scope module Bit2 $end
    $var wire 1 + A $end
    $var wire 1 , B $end
    $var wire 1 % SEL $end
    $var wire 1 5 CI $end
    $var wire 1 6 Y $end
    $var wire 1 7 CO $end
   $upscope $end
   $scope module Bit3 $end
    $var wire 1 - A $end
    $var wire 1 . B $end
    $var wire 1 % SEL $end
    $var wire 1 7 CI $end
    $var wire 1 8 Y $end
    $var wire 1 0 CO $end
   $upscope $end
  $upscope $end
 $upscope $end
$enddefinitions $end


#0
b0011 #
b0011 $
0%
0&
1'
1(
1)
1*
0+
0,
0-
0.
b0110 /
00
b011 1
02
13
14
15
16
07
08
#5
b0101 #
b1010 $
0(
0)
1+
1.
b1111 /
b000 1
12
03
05
18
#10
b0100 #
b0011 $
0'
1(
0.
b0111 /
08
#15
b1010 #
b1011 $
1)
0+
1-
1.
b0101 /
10
b010 1
04
15
#20
b0011 #
b0011 $
1%
1'
0-
0.
b0000 /
00
b000 1
02
05
06
#25
b0101 #
b1010 $
0(
0)
1+
1.
b1011 /
10
b010 1
12
14
15
18
#30
b0100 #
b0011 $
0'
1(
0.
b0001 /
00
b011 1
13
04
08
#35
b1010 #
b1011 $
1)
0+
1-
1.
b1111 /
10
b111 1
14
16
17
18
