andgate.sv
`timescale 1ns/1ns

module andgate (a, b, c);
    input logic a, b;
    output logic c;


    assign c = (a&b);

endmodule

Gates/xnorgate.sv
`timescale 1ns/1ns

module xnorgate (a, b, c);
    input logic a, b;
    output logic c;

    assign c = !(a^b);

endmodule

DigitalLogic/sistema_y.sv
`timescale 1ns/1ns

module sistema_y(A, B, E);

    input logic [3:0] A, B;
    output logic E;

    logic [5:0] T;

    xnorgate xnor1 ( .a(A[3]), .b(B[3]), .c(T[3]));
    xnorgate xnor2 ( .a(A[2]), .b(B[2]), .c(T[2]));
    xnorgate xnor3 ( .a(A[1]), .b(B[1]), .c(T[1]));
    xnorgate xnor4 ( .a(A[0]), .b(B[0]), .c(T[0]));

    andgate and1 ( .a(T[3]), .b(T[2]), .c(T[4]));
    andgate and2 ( .a(T[1]), .b(T[0]), .c(T[5]));
    andgate and3 ( .a(T[4]), .b(T[5]), .c(E));

endmodule

sistema_y_tb.sv
module sistema_y_tb;
    logic [3:0] A, B;
    logic E;

    sistema_y sy1 (.A(A), .B(B), .E(E));

    initial begin
        A = 4'b0000;
        B = 4'b0000;

        #5
        A = 4'b0001;
        B = 4'b0001;

        #5
        A = 4'b0010;
        B = 4'b0010;

        #5
        A = 4'b0011;
        B = 4'b0011;

        #5
        A = 4'b0100;
        B = 4'b0100;

        #5
        A = 4'b0101;
        B = 4'b0101;

        #5
        A = 4'b0110;
        B = 4'b0110;

        #5
        A = 4'b0111;
        B = 4'b0100;

        #5
        A = 4'b1000;
        B = 4'b0111;

        #5
        A = 4'b1001;
        B = 4'b0100; 

        #5
        A = 4'b1010;
        B = 4'b0000;

        #5
        A = 4'b1011;
        B = 4'b1110;

        #5
        A = 4'b1100;
        B = 4'b0001;

        #5
        A = 4'b1101;
        B = 4'b1101;

        #5
        A = 4'b1110;
        B = 4'b1110;

        #5
        A = 4'b1111;
        B = 4'b1110;

        #5;
    end

    initial begin
        $display(" A == B?" );
        $monitor($time, "  %b %b %b", A, B, E);
    end

    initial begin
        $dumpfile("sistema_y.vcd");
        $dumpvars("");
    end


endmodule

sistema_y.vcd
$version Generated by VerilatedVcd $end
$timescale 1ns $end
 $scope module $rootio $end
 $upscope $end
 $scope module sistema_y_tb $end
  $var wire 4 # A [3:0] $end
  $var wire 4 $ B [3:0] $end
  $var wire 1 - E $end
  $scope module sy1 $end
   $var wire 4 # A [3:0] $end
   $var wire 4 $ B [3:0] $end
   $var wire 1 - E $end
   $var wire 6 . T [5:0] $end
   $scope module and1 $end
    $var wire 1 / a $end
    $var wire 1 0 b $end
    $var wire 1 1 c $end
   $upscope $end
   $scope module and2 $end
    $var wire 1 2 a $end
    $var wire 1 3 b $end
    $var wire 1 4 c $end
   $upscope $end
   $scope module and3 $end
    $var wire 1 1 a $end
    $var wire 1 4 b $end
    $var wire 1 - c $end
   $upscope $end
   $scope module xnor1 $end
    $var wire 1 % a $end
    $var wire 1 & b $end
    $var wire 1 / c $end
   $upscope $end
   $scope module xnor2 $end
    $var wire 1 ' a $end
    $var wire 1 ( b $end
    $var wire 1 0 c $end
   $upscope $end
   $scope module xnor3 $end
    $var wire 1 ) a $end
    $var wire 1 * b $end
    $var wire 1 2 c $end
   $upscope $end
   $scope module xnor4 $end
    $var wire 1 + a $end
    $var wire 1 , b $end
    $var wire 1 3 c $end
   $upscope $end
  $upscope $end
 $upscope $end
$enddefinitions $end


#0
b0000 #
b0000 $
0%
0&
0'
0(
0)
0*
0+
0,
1-
b111111 .
1/
10
11
12
13
14
#5
b0001 #
b0001 $
1+
1,
#10
b0010 #
b0010 $
1)
1*
0+
0,
#15
b0011 #
b0011 $
1+
1,
#20
b0100 #
b0100 $
1'
1(
0)
0*
0+
0,
#25
b0101 #
b0101 $
1+
1,
#30
b0110 #
b0110 $
1)
1*
0+
0,
#35
b0111 #
b0100 $
0*
1+
0-
b011100 .
02
03
04
#40
b1000 #
b0111 $
1%
0'
0)
1*
0+
1,
b000000 .
0/
00
01
#45
b1001 #
b0100 $
0*
1+
0,
b000010 .
12
#50
b1010 #
b0000 $
0(
1)
0+
b000101 .
10
02
13
#55
b1011 #
b1110 $
1&
1(
1*
1+
b001010 .
1/
00
12
03
#60
b1100 #
b0001 $
0&
1'
0(
0)
0*
0+
1,
b000010 .
0/
#65
b1101 #
b1101 $
1&
1(
1+
1-
b111111 .
1/
10
11
13
14
#70
b1110 #
b1110 $
1)
1*
0+
0,
#75
b1111 #
1+
0-
b011110 .
03
04
