Gates/fa.sv
`timescale 1ns/1ns

module fa (A, B, CI, S, CO);
    input logic A, B, CI;
    output logic S, CO;

    logic T;

    assign T = A^B;

    assign S = T^CI;
    assign CO = (A&B)|(CI&T);

endmodule

fa_tb.sv
module fa_tb;
    logic A, B, CI;
    logic S, CO;

    fa fag( .A(A), .B(B), .CI(CI), .S(S), .CO(CO));

    initial begin
        A = 1'b0;
        B = 1'b0;
        CI = 1'b0;

        #5
        A = 1'b1;
        B = 1'b0;
        CI = 1'b0;

        #5
        A = 1'b0;
        B = 1'b1;
        CI = 1'b0;

        #5
        A = 1'b1;
        B = 1'b1;
        CI = 1'b0;

        #5
        A = 1'b0;
        B = 1'b0;
        CI = 1'b1;

        #5
        A = 1'b1;
        B = 1'b0;
        CI = 1'b1;

        #5
        A = 1'b0;
        B = 1'b1;
        CI = 1'b1;

        #5
        A = 1'b1;
        B = 1'b1;
        CI = 1'b1;

        #5;
    end

    initial begin
        $display("                  Tempo    Entradas    Saídas");
        $display("                            A B CI      S Co ");
        $display("                  =====    ========    ======");
        $monitor($time, "        %b %b %b         %b %b     ", A, B, CI, S, CO);
    end

    initial begin
        $dumpfile("fa.vcd");
        $dumpvars("");
    end

endmodule

Gates/fa.vcd
$version Generated by VerilatedVcd $end
$timescale 1ps $end
 $scope module $rootio $end
 $upscope $end
 $scope module fa_tb $end
  $var wire 1 & A $end
  $var wire 1 ' B $end
  $var wire 1 ( CI $end
  $var wire 1 # S $end
  $var wire 1 $ CO $end
  $scope module fag $end
   $var wire 1 & A $end
   $var wire 1 ' B $end
   $var wire 1 ( CI $end
   $var wire 1 # S $end
   $var wire 1 $ CO $end
   $var wire 1 % T $end
  $upscope $end
 $upscope $end
$enddefinitions $end


#0
0#
0$
0%
0&
0'
0(
#5
1#
1%
1&
#10
0&
1'
#15
0#
1$
0%
1&
#20
1#
0$
0&
0'
1(
#25
0#
1$
1%
1&
#30
0&
1'
#35
1#
0%
1&
