andgate.sv
`timescale 1ns/1ns

module andgate (a, b, c);
    input logic a, b;
    output logic c;


    assign c = (a&b);

endmodule

Gates/xnorgate.sv
`timescale 1ns/1ns

module xnorgate (a, b, c);
    input logic a, b;
    output logic c;

    assign c = !(a^b);

endmodule

DigitalLogic/CompConst.sv
`timescale 1ns/1ns

module CompConst(A, E);

    input logic [3:0] A;
    output logic E;

    logic [3:0] B;
    logic [5:0] T;

    assign B = 4'b0101;

    xnorgate xnor1 ( .a(A[3]), .b(B[3]), .c(T[3]));
    xnorgate xnor2 ( .a(A[2]), .b(B[2]), .c(T[2]));
    xnorgate xnor3 ( .a(A[1]), .b(B[1]), .c(T[1]));
    xnorgate xnor4 ( .a(A[0]), .b(B[0]), .c(T[0]));

    andgate and1 ( .a(T[3]), .b(T[2]), .c(T[4]));
    andgate and2 ( .a(T[1]), .b(T[0]), .c(T[5]));
    andgate and3 ( .a(T[4]), .b(T[5]), .c(E));

endmodule

CompConst_tb.sv
module CompConst_tb;
    logic [3:0] A;
    logic E;

    CompConst cc1 (.A(A), .E(E));

    initial begin
        A = 4'b0000;

        #5
        A = 4'b0001;

        #5
        A = 4'b0010;

        #5
        A = 4'b0011;

        #5
        A = 4'b0100;

        #5
        A = 4'b0101;

        #5
        A = 4'b0110;

        #5
        A = 4'b0111;

        #5
        A = 4'b1000;

        #5
        A = 4'b1001;

        #5
        A = 4'b1010;

        #5
        A = 4'b1011;

        #5
        A = 4'b1100;

        #5
        A = 4'b1101;

        #5
        A = 4'b1110;

        #5
        A = 4'b1111;

        #5;
    end

    initial begin
        $display(" A == B? B == 4'b0101" );
        $monitor($time, "  %b 0101 %b", A, E);
    end

    initial begin
        $dumpfile("CompConst.vcd");
        $dumpvars("");
    end


endmodule

DigitalLogic/CompConst.vcd
$version Generated by VerilatedVcd $end
$timescale 1ns $end
 $scope module $rootio $end
 $upscope $end
 $scope module CompConst_tb $end
  $var wire 4 # A [3:0] $end
  $var wire 1 * E $end
  $scope module cc1 $end
   $var wire 4 # A [3:0] $end
   $var wire 1 * E $end
   $var wire 4 . B [3:0] $end
   $var wire 6 - T [5:0] $end
   $scope module and1 $end
    $var wire 1 $ a $end
    $var wire 1 % b $end
    $var wire 1 + c $end
   $upscope $end
   $scope module and2 $end
    $var wire 1 & a $end
    $var wire 1 ' b $end
    $var wire 1 , c $end
   $upscope $end
   $scope module and3 $end
    $var wire 1 + a $end
    $var wire 1 , b $end
    $var wire 1 * c $end
   $upscope $end
   $scope module xnor1 $end
    $var wire 1 ( a $end
    $var wire 1 / b $end
    $var wire 1 $ c $end
   $upscope $end
   $scope module xnor2 $end
    $var wire 1 % a $end
    $var wire 1 0 b $end
    $var wire 1 % c $end
   $upscope $end
   $scope module xnor3 $end
    $var wire 1 ) a $end
    $var wire 1 / b $end
    $var wire 1 & c $end
   $upscope $end
   $scope module xnor4 $end
    $var wire 1 ' a $end
    $var wire 1 0 b $end
    $var wire 1 ' c $end
   $upscope $end
  $upscope $end
 $upscope $end
$enddefinitions $end


#0
b0000 #
1$
0%
1&
0'
0(
0)
0*
0+
0,
b001010 -
b0101 .
0/
10
#5
b0001 #
1'
1,
b101011 -
#10
b0010 #
0&
0'
1)
0,
b001000 -
#15
b0011 #
1'
b001001 -
#20
b0100 #
1%
1&
0'
0)
1+
b011110 -
#25
b0101 #
1'
1*
1,
b111111 -
#30
b0110 #
0&
0'
1)
0*
0,
b011100 -
#35
b0111 #
1'
b011101 -
#40
b1000 #
0$
0%
1&
0'
1(
0)
0+
b000010 -
#45
b1001 #
1'
1,
b100011 -
#50
b1010 #
0&
0'
1)
0,
b000000 -
#55
b1011 #
1'
b000001 -
#60
b1100 #
1%
1&
0'
0)
b000110 -
#65
b1101 #
1'
1,
b100111 -
#70
b1110 #
0&
0'
1)
0,
b000100 -
#75
b1111 #
1'
b000101 -
