LUT3.sv
// $Header: /devl/xcs/repo/env/Databases/CAEInterfaces/verunilibs/data/unisims/LUT3.v,v 1.7 2007/05/23 21:43:39 patrickp Exp $
///////////////////////////////////////////////////////////////////////////////
// Copyright (c) 1995/2004 Xilinx, Inc.
// All Right Reserved.
///////////////////////////////////////////////////////////////////////////////
//   ____  ____
//  /   /\/   /
// /___/  \  /    Vendor : Xilinx
// \   \   \/     Version : 10.1
//  \   \         Description : Xilinx Functional Simulation Library Component
//  /   /                  3-input Look-Up-Table with General Output
// /___/   /\     Filename : LUT3.v
// \   \  /  \    Timestamp : Thu Mar 25 16:42:54 PST 2004
//  \___\/\___\
//
// Revision:
//    03/23/04 - Initial version.
//    02/04/05 - Rev 0.0.1 Replace premitive with function; Remove buf.
//    05/23/07 - Changed timescale to 1 ps / 1 ps.

`timescale  1 ns / 1 ns


module LUT3 (O, I0, I1, I2);

    parameter INIT = 8'h00;

    input I0, I1, I2;

    output logic O;

    logic tmp;
  
    always_ff @(  I2 or  I1 or  I0 )  begin
      tmp <=  I0 ^ I1  ^ I2;
      if ( tmp == 0 || tmp == 1)
           O <= INIT[{I2, I1, I0}];
      else
           O <= lut3_mux4 ( {1'b0, 1'b0, lut3_mux4 (INIT[7:4], {I1, I0}),
                          lut3_mux4 (INIT[3:0], {I1, I0}) }, {1'b0, I2});
    end

  function lut3_mux4;
  input [3:0] d;
  input [1:0] s;

  begin
       if ((s[1]^s[0] ==1) || (s[1]^s[0] ==0))
           lut3_mux4 = d[s];
         else if ((d[0] === d[1]) && (d[2] === d[3]) && (d[0] === d[2]))
           lut3_mux4 = d[0];
         else if ((s[1] == 0) && (d[0] === d[1]))
           lut3_mux4 = d[0];
         else if ((s[1] == 1) && (d[2] === d[3]))
           lut3_mux4 = d[2];
         else if ((s[0] == 0) && (d[0] === d[2]))
           lut3_mux4 = d[0];
         else if ((s[0] == 1) && (d[1] === d[3]))
           lut3_mux4 = d[1];
         else
           lut3_mux4 = 1'bx;
   end
   endfunction

endmodule

ArchitectureFPGA/Ex2.sv
`timescale 1ns/1ns

module Ex2 (A, Y);
    input logic [3:0] A;
    output logic Y;

    wire [4:0] w;

    LUT3 #(.INIT(8'h01)) L3NOR1 ( .O(w[0]), .I0(A[3]), .I1(A[2]), .I2(A[1]));

    LUT3 #(.INIT(8'h80)) L3AND1 ( .O(w[1]), .I0(A[3]), .I1(A[2]), .I2(A[0]));

    LUT3 #(.INIT(8'h80)) L3AND2 ( .O(w[2]), .I0(A[3]), .I1(A[2]), .I2(A[1]));
    
    LUT3 #(.INIT(8'h01)) L3NOR2 ( .O(w[3]), .I0(A[3]), .I1(A[2]), .I2(A[0]));

    LUT3 #(.INIT(8'hFE)) L3OR1 ( .O(w[4]), .I0(w[2]), .I1(w[1]), .I2(w[0]));
    LUT3 #(.INIT(8'hFE)) L3OR2 ( .O(Y), .I0(w[3]), .I1(w[3]), .I2(w[4]));

endmodule

Ex2_tb.sv
module Ex2_tb;

    logic [3:0] A;
    logic Y;

    Ex2 ex2t( .A(A), .Y(Y));

    initial begin
        integer i;

        for (i=0;i<16;i++) begin
            A = i[3:0];
            
            #5;
            $display($time,("   %b || %b "), A, Y);
        end
    end

    /*initial begin
        $monitor($time, ("   %b || %b "), A, Y);
    end*/

    initial begin
        $dumpfile("Ex2.vcd");
        $dumpvars("");
    end

endmodule

ArchitectureFPGA/Ex2.vcd
$version Generated by VerilatedVcd $end
$timescale 1ns $end
 $scope module $rootio $end
 $upscope $end
 $scope module Ex2_tb $end
  $var wire 4 + A [3:0] $end
  $var wire 1 , Y $end
  $scope module ex2t $end
   $var wire 4 + A [3:0] $end
   $var wire 1 , Y $end
   $var wire 5 - w [4:0] $end
   $scope module L3AND1 $end
    $var wire 8 6 INIT [7:0] $end
    $var wire 1 # I0 $end
    $var wire 1 $ I1 $end
    $var wire 1 % I2 $end
    $var wire 1 . O $end
    $var wire 1 / tmp $end
   $upscope $end
   $scope module L3AND2 $end
    $var wire 8 6 INIT [7:0] $end
    $var wire 1 # I0 $end
    $var wire 1 $ I1 $end
    $var wire 1 & I2 $end
    $var wire 1 ' O $end
    $var wire 1 ( tmp $end
   $upscope $end
   $scope module L3NOR1 $end
    $var wire 8 7 INIT [7:0] $end
    $var wire 1 # I0 $end
    $var wire 1 $ I1 $end
    $var wire 1 & I2 $end
    $var wire 1 ) O $end
    $var wire 1 * tmp $end
   $upscope $end
   $scope module L3NOR2 $end
    $var wire 8 7 INIT [7:0] $end
    $var wire 1 # I0 $end
    $var wire 1 $ I1 $end
    $var wire 1 % I2 $end
    $var wire 1 0 O $end
    $var wire 1 1 tmp $end
   $upscope $end
   $scope module L3OR1 $end
    $var wire 8 8 INIT [7:0] $end
    $var wire 1 ' I0 $end
    $var wire 1 . I1 $end
    $var wire 1 ) I2 $end
    $var wire 1 2 O $end
    $var wire 1 3 tmp $end
   $upscope $end
   $scope module L3OR2 $end
    $var wire 8 8 INIT [7:0] $end
    $var wire 1 0 I0 $end
    $var wire 1 0 I1 $end
    $var wire 1 2 I2 $end
    $var wire 1 , O $end
    $var wire 1 4 tmp $end
   $upscope $end
  $upscope $end
  $scope module unnamedblk1 $end
   $var wire 32 5 i [31:0] $end
  $upscope $end
 $upscope $end
$enddefinitions $end


#0
0#
0$
0%
0&
0'
0(
1)
0*
b0000 +
1,
b11001 -
0.
0/
10
01
12
13
14
b00000000000000000000000000000000 5
b10000000 6
b00000001 7
b11111110 8
#5
1%
b0001 +
b10001 -
1/
00
11
b00000000000000000000000000000001 5
#10
0%
1&
1(
0)
1*
b0010 +
b01000 -
0/
10
01
02
03
04
b00000000000000000000000000000010 5
#15
1%
b0011 +
0,
b00000 -
1/
00
11
b00000000000000000000000000000011 5
#20
1$
0%
0&
b0100 +
b00000000000000000000000000000100 5
#25
1%
b0101 +
0/
01
b00000000000000000000000000000101 5
#30
0%
1&
0(
0*
b0110 +
1/
11
b00000000000000000000000000000110 5
#35
1%
b0111 +
0/
01
b00000000000000000000000000000111 5
#40
1#
0$
0%
0&
1(
1*
b1000 +
1/
11
b00000000000000000000000000001000 5
#45
1%
b1001 +
0/
01
b00000000000000000000000000001001 5
#50
0%
1&
0(
0*
b1010 +
1/
11
b00000000000000000000000000001010 5
#55
1%
b1011 +
0/
01
b00000000000000000000000000001011 5
#60
1$
0%
0&
b1100 +
b00000000000000000000000000001100 5
#65
1%
b1101 +
1,
b10010 -
1.
1/
11
12
13
14
b00000000000000000000000000001101 5
#70
0%
1&
1'
1(
1*
b1110 +
b10100 -
0.
0/
01
b00000000000000000000000000001110 5
#75
1%
b1111 +
b10110 -
1.
1/
11
03
b00000000000000000000000000001111 5
#80
b00000000000000000000000000010000 5
