LUT3.sv
// $Header: /devl/xcs/repo/env/Databases/CAEInterfaces/verunilibs/data/unisims/LUT3.v,v 1.7 2007/05/23 21:43:39 patrickp Exp $
///////////////////////////////////////////////////////////////////////////////
// Copyright (c) 1995/2004 Xilinx, Inc.
// All Right Reserved.
///////////////////////////////////////////////////////////////////////////////
//   ____  ____
//  /   /\/   /
// /___/  \  /    Vendor : Xilinx
// \   \   \/     Version : 10.1
//  \   \         Description : Xilinx Functional Simulation Library Component
//  /   /                  3-input Look-Up-Table with General Output
// /___/   /\     Filename : LUT3.v
// \   \  /  \    Timestamp : Thu Mar 25 16:42:54 PST 2004
//  \___\/\___\
//
// Revision:
//    03/23/04 - Initial version.
//    02/04/05 - Rev 0.0.1 Replace premitive with function; Remove buf.
//    05/23/07 - Changed timescale to 1 ps / 1 ps.

`timescale  1 ns / 1 ns


module LUT3 (O, I0, I1, I2);

    parameter INIT = 8'h00;

    input I0, I1, I2;

    output logic O;

    logic tmp;
  
    always_ff @(  I2 or  I1 or  I0 )  begin
      tmp <=  I0 ^ I1  ^ I2;
      if ( tmp == 0 || tmp == 1)
           O <= INIT[{I2, I1, I0}];
      else
           O <= lut3_mux4 ( {1'b0, 1'b0, lut3_mux4 (INIT[7:4], {I1, I0}),
                          lut3_mux4 (INIT[3:0], {I1, I0}) }, {1'b0, I2});
    end

  function lut3_mux4;
  input [3:0] d;
  input [1:0] s;

  begin
       if ((s[1]^s[0] ==1) || (s[1]^s[0] ==0))
           lut3_mux4 = d[s];
         else if ((d[0] === d[1]) && (d[2] === d[3]) && (d[0] === d[2]))
           lut3_mux4 = d[0];
         else if ((s[1] == 0) && (d[0] === d[1]))
           lut3_mux4 = d[0];
         else if ((s[1] == 1) && (d[2] === d[3]))
           lut3_mux4 = d[2];
         else if ((s[0] == 0) && (d[0] === d[2]))
           lut3_mux4 = d[0];
         else if ((s[0] == 1) && (d[1] === d[3]))
           lut3_mux4 = d[1];
         else
           lut3_mux4 = 1'bx;
   end
   endfunction

endmodule

LUT3_tb.sv
module LUT3_tb;
  logic O, I0, I1, I2;
  
  // instantiating the module to map connections
  LUT3 #(.INIT(8'hFE)) LUT3_INST(.I0(I0), .I1(I1), .I2(I2), .O(O));
  
  initial
    begin
      I2 = 1'b0;
      I1 = 1'b0;
      I0 = 1'b0;

      #5
      I2 = 1'b0;
      I1 = 1'b0;
      I0 = 1'b1;    
      
      #5
      I2 = 1'b0;
      I1 = 1'b1;
      I0 = 1'b0;
      
      #5
      I2 = 1'b0;
      I1 = 1'b1;
      I0 = 1'b1;
      
      #5
      I2 = 1'b1;
      I1 = 1'b0;
      I0 = 1'b0;
      
      #5
      I2 = 1'b1;
      I1 = 1'b0;
      I0 = 1'b1;
      
      #5
      I2 = 1'b1;
      I1 = 1'b1;
      I0 = 1'b0;
      
      #5
      I2 = 1'b1;
      I1 = 1'b1;
      I0 = 1'b1;

      #5;
    end
  
    initial
    begin
      $display("                Tempo   Entradas LUT3   Saídas");
      $display("                         I2   I1   I0       O");
      $display("                ====   ================   ====");
      $monitor($time,"     %b    %b    %b       %b", I2, I1, I0,  O);
    end

    initial begin
        $dumpfile("LUT3.vcd");
        $dumpvars("");
    end
  
endmodule

ArchitectureFPGA/LUT3.vcd
$version Generated by VerilatedVcd $end
$timescale 1ns $end
 $scope module $rootio $end
 $upscope $end
 $scope module LUT3_tb $end
  $var wire 1 # O $end
  $var wire 1 $ I0 $end
  $var wire 1 % I1 $end
  $var wire 1 & I2 $end
  $scope module LUT3_INST $end
   $var wire 8 ( INIT [7:0] $end
   $var wire 1 $ I0 $end
   $var wire 1 % I1 $end
   $var wire 1 & I2 $end
   $var wire 1 # O $end
   $var wire 1 ' tmp $end
  $upscope $end
 $upscope $end
$enddefinitions $end


#0
0#
0$
0%
0&
0'
b11111110 (
#5
1#
1$
1'
#10
0$
1%
#15
1$
0'
#20
0$
0%
1&
1'
#25
1$
0'
#30
0$
1%
#35
1$
1'
